smart_progress.py
smart_progress-1.0.2.dist-info/DESCRIPTION.rst
smart_progress-1.0.2.dist-info/METADATA
smart_progress-1.0.2.dist-info/RECORD
smart_progress-1.0.2.dist-info/WHEEL
smart_progress-1.0.2.dist-info/metadata.json
smart_progress-1.0.2.dist-info/top_level.txt
