Metadata-Version: 2.0
Name: smart-progress
Version: 1.0.2
Summary: Smart progressbar with multiple backends selected depending on the environment
Home-page: https://github.com/flying-sheep/smart-progress
Author: Philipp A.
Author-email: flying-sheep@web.de
License: GPLv3
Keywords: progress progressbar ipython jupyter console
Platform: UNKNOWN
Classifier: Development Status :: 4 - Beta
Classifier: Intended Audience :: Developers
Classifier: Intended Audience :: Science/Research
Classifier: Intended Audience :: System Administrators
Classifier: Environment :: Console
Classifier: Environment :: Web Environment
Classifier: License :: OSI Approved :: GNU General Public License v3 (GPLv3)
Classifier: Programming Language :: Python :: 3
Classifier: Programming Language :: Python :: 3.2
Classifier: Programming Language :: Python :: 3.3
Classifier: Programming Language :: Python :: 3.4
Classifier: Topic :: Software Development :: Widget Sets
Classifier: Topic :: Utilities
Requires-Dist: click
Provides-Extra: ipynb
Requires-Dist: ipywidgets; extra == 'ipynb'
